gql/__init__.py
gql/client.py
gql/dsl.py
gql/gql.py
gql/utils.py
gql/transport/__init__.py
gql/transport/http.py
gql/transport/local_schema.py
gql/transport/requests.py
gql_fork-0.2.0.dist-info/DESCRIPTION.rst
gql_fork-0.2.0.dist-info/METADATA
gql_fork-0.2.0.dist-info/RECORD
gql_fork-0.2.0.dist-info/WHEEL
gql_fork-0.2.0.dist-info/metadata.json
gql_fork-0.2.0.dist-info/top_level.txt
