Metadata-Version: 2.0
Name: gql-fork
Version: 0.2.0
Summary: fork version of gql: GraphQL client for Python
Home-page: https://github.com/Yoctol/gql-fork
Author: cph
Author-email: cph@yoctol.com
License: MIT
Keywords: api graphql protocol rest relay gql client
Platform: UNKNOWN
Classifier: Development Status :: 3 - Alpha
Classifier: Intended Audience :: Developers
Classifier: Topic :: Software Development :: Libraries
Classifier: Programming Language :: Python :: 2
Classifier: Programming Language :: Python :: 2.7
Classifier: Programming Language :: Python :: 3
Classifier: Programming Language :: Python :: 3.3
Classifier: Programming Language :: Python :: 3.4
Classifier: Programming Language :: Python :: 3.5
Classifier: Programming Language :: Python :: Implementation :: PyPy
Requires-Dist: six (>=1.10.0)
Requires-Dist: graphql-core (>=0.5.0)
Requires-Dist: promise (>=0.4.0)
